usaepay/__init__.py
usaepay/api.py
usaepay/mockhandler.py
usaepay/batches/__init__.py
usaepay/batches/current/__init__.py
usaepay/batches/current/close/__init__.py
usaepay/batches/current/transactions/__init__.py
usaepay/batches/transactions/__init__.py
usaepay/customers/__init__.py
usaepay/customers/billing_schedules/__init__.py
usaepay/customers/billing_schedules/billing_schedule_rules/__init__.py
usaepay/customers/billing_schedules/billing_schedule_rules/bulk/__init__.py
usaepay/customers/bulk/__init__.py
usaepay/customers/disable/__init__.py
usaepay/customers/enable/__init__.py
usaepay/customers/payment_methods/__init__.py
usaepay/customers/transactions/__init__.py
usaepay/invoices/__init__.py
usaepay/invoices/bulk/__init__.py
usaepay/invoices/bulk/send/__init__.py
usaepay/invoices/cancel/__init__.py
usaepay/invoices/columns/__init__.py
usaepay/invoices/defaults/__init__.py
usaepay/invoices/nextnum/__init__.py
usaepay/invoices/payments/__init__.py
usaepay/invoices/send/__init__.py
usaepay/middleware/__init__.py
usaepay/middleware/webhook.py
usaepay/paymentengine/__init__.py
usaepay/paymentengine/devices/__init__.py
usaepay/paymentengine/devices/kick/__init__.py
usaepay/paymentengine/devices/settings/__init__.py
usaepay/paymentengine/devices/terminal_config/__init__.py
usaepay/paymentengine/payrequests/__init__.py
usaepay/paymentengine/payrequests/confirm/__init__.py
usaepay/products/__init__.py
usaepay/products/categories/__init__.py
usaepay/publickey/__init__.py
usaepay/tokens/__init__.py
usaepay/transactions/__init__.py
usaepay/transactions/receipts/__init__.py
usaepay/transactions/send/__init__.py
usaepay-2.1.6.dist-info/LICENSE.txt
usaepay-2.1.6.dist-info/METADATA
usaepay-2.1.6.dist-info/WHEEL
usaepay-2.1.6.dist-info/top_level.txt
usaepay-2.1.6.dist-info/RECORD
