Metadata-Version: 2.1
Name: usaepay
Version: 2.1.6
Summary: sdk for usaepay rest api
Home-page: https://secure.usaepay.com/
Author: usaepay
Author-email: 706@usaepay.com
Classifier: Programming Language :: Python :: 3
Classifier: License :: OSI Approved :: MIT License
Classifier: Operating System :: OS Independent
Requires-Python: >=3.6
License-File: LICENSE.txt
Requires-Dist: requests
